settings_holder/__init__.py
settings_holder/fixtures.py
settings_holder/holder.py
settings_holder/py.typed
settings_holder/utils.py
django_settings_holder-0.3.0.dist-info/LICENSE
django_settings_holder-0.3.0.dist-info/METADATA
django_settings_holder-0.3.0.dist-info/WHEEL
django_settings_holder-0.3.0.dist-info/entry_points.txt
django_settings_holder-0.3.0.dist-info/RECORD
