Metadata-Version: 2.3
Name: django-settings-holder
Version: 0.3.0
Summary: Object that allows settings to be accessed with attributes.
Home-page: https://mrthearman.github.io/django-settings-holder
License: MIT
Keywords: django,settings,holder
Author: Matti Lamppu
Author-email: lamppu.matti.akseli@gmail.com
Requires-Python: >=3.10,<4
Classifier: Environment :: Web Environment
Classifier: Intended Audience :: Developers
Classifier: Programming Language :: Python
Classifier: Programming Language :: Python :: 3
Classifier: Programming Language :: Python :: 3 :: Only
Classifier: Programming Language :: Python :: 3.10
Classifier: Programming Language :: Python :: 3.11
Classifier: Programming Language :: Python :: 3.12
Classifier: Programming Language :: Python :: 3.13
Classifier: Framework :: Django
Classifier: Framework :: Django :: 4.2
Classifier: Framework :: Django :: 5.0
Classifier: Framework :: Django :: 5.1
Classifier: Framework :: Django :: 5.2
Requires-Dist: Django (>=4.2)
Project-URL: Bug Tracker, https://github.com/MrThearMan/django-settings-holder/issues
Project-URL: Documentation, https://mrthearman.github.io/django-settings-holder
Project-URL: Repository, https://github.com/MrThearMan/django-settings-holder
